[{"count":0,"bin_start":65927.5,"bin_end":65927.54},{"count":0,"bin_start":65927.54,"bin_end":65927.58},{"count":0,"bin_start":65927.58,"bin_end":65927.62},{"count":0,"bin_start":65927.62,"bin_end":65927.66},{"count":0,"bin_start":65927.66,"bin_end":65927.7},{"count":0,"bin_start":65927.7,"bin_end":65927.74},{"count":0,"bin_start":65927.74,"bin_end":65927.78},{"count":0,"bin_start":65927.78,"bin_end":65927.82},{"count":0,"bin_start":65927.82,"bin_end":65927.86},{"count":0,"bin_start":65927.86,"bin_end":65927.9},{"count":0,"bin_start":65927.9,"bin_end":65927.94},{"count":0,"bin_start":65927.94,"bin_end":65927.98},{"count":2,"bin_start":65927.98,"bin_end":65928.02},{"count":0,"bin_start":65928.02,"bin_end":65928.06},{"count":0,"bin_start":65928.06,"bin_end":65928.1},{"count":0,"bin_start":65928.1,"bin_end":65928.14},{"count":0,"bin_start":65928.14,"bin_end":65928.18},{"count":0,"bin_start":65928.18,"bin_end":65928.22},{"count":0,"bin_start":65928.22,"bin_end":65928.26},{"count":0,"bin_start":65928.26,"bin_end":65928.3},{"count":0,"bin_start":65928.3,"bin_end":65928.34},{"count":0,"bin_start":65928.34,"bin_end":65928.38},{"count":0,"bin_start":65928.38,"bin_end":65928.42},{"count":0,"bin_start":65928.42,"bin_end":65928.46},{"count":0,"bin_start":65928.46,"bin_end":65928.5}]