[{"count":0,"bin_start":105335.5,"bin_end":105335.54},{"count":0,"bin_start":105335.54,"bin_end":105335.58},{"count":0,"bin_start":105335.58,"bin_end":105335.62},{"count":0,"bin_start":105335.62,"bin_end":105335.66},{"count":0,"bin_start":105335.66,"bin_end":105335.7},{"count":0,"bin_start":105335.7,"bin_end":105335.74},{"count":0,"bin_start":105335.74,"bin_end":105335.78},{"count":0,"bin_start":105335.78,"bin_end":105335.82},{"count":0,"bin_start":105335.82,"bin_end":105335.86},{"count":0,"bin_start":105335.86,"bin_end":105335.9},{"count":0,"bin_start":105335.9,"bin_end":105335.94},{"count":0,"bin_start":105335.94,"bin_end":105335.98},{"count":1,"bin_start":105335.98,"bin_end":105336.02},{"count":0,"bin_start":105336.02,"bin_end":105336.06},{"count":0,"bin_start":105336.06,"bin_end":105336.1},{"count":0,"bin_start":105336.1,"bin_end":105336.14},{"count":0,"bin_start":105336.14,"bin_end":105336.18},{"count":0,"bin_start":105336.18,"bin_end":105336.22},{"count":0,"bin_start":105336.22,"bin_end":105336.26},{"count":0,"bin_start":105336.26,"bin_end":105336.3},{"count":0,"bin_start":105336.3,"bin_end":105336.34},{"count":0,"bin_start":105336.34,"bin_end":105336.38},{"count":0,"bin_start":105336.38,"bin_end":105336.42},{"count":0,"bin_start":105336.42,"bin_end":105336.46},{"count":0,"bin_start":105336.46,"bin_end":105336.5}]