[{"count":1,"bin_start":77892.0,"bin_end":79779.84},{"count":0,"bin_start":79779.84,"bin_end":81667.68},{"count":0,"bin_start":81667.68,"bin_end":83555.52},{"count":0,"bin_start":83555.52,"bin_end":85443.36},{"count":0,"bin_start":85443.36,"bin_end":87331.2},{"count":0,"bin_start":87331.2,"bin_end":89219.04},{"count":0,"bin_start":89219.04,"bin_end":91106.88},{"count":0,"bin_start":91106.88,"bin_end":92994.72},{"count":0,"bin_start":92994.72,"bin_end":94882.56},{"count":0,"bin_start":94882.56,"bin_end":96770.4},{"count":0,"bin_start":96770.4,"bin_end":98658.24},{"count":0,"bin_start":98658.24,"bin_end":100546.08},{"count":0,"bin_start":100546.08,"bin_end":102433.92},{"count":0,"bin_start":102433.92,"bin_end":104321.76},{"count":0,"bin_start":104321.76,"bin_end":106209.6},{"count":0,"bin_start":106209.6,"bin_end":108097.44},{"count":1,"bin_start":108097.44,"bin_end":109985.28},{"count":0,"bin_start":109985.28,"bin_end":111873.12},{"count":0,"bin_start":111873.12,"bin_end":113760.96},{"count":0,"bin_start":113760.96,"bin_end":115648.8},{"count":0,"bin_start":115648.8,"bin_end":117536.64},{"count":0,"bin_start":117536.64,"bin_end":119424.48},{"count":0,"bin_start":119424.48,"bin_end":121312.32},{"count":0,"bin_start":121312.32,"bin_end":123200.16},{"count":1,"bin_start":123200.16,"bin_end":125088.0}]